LICENSE
MANIFEST.in
README.md
setup.py
lynx/__init__.py
lynx/decoder.py
lynx/encoder.py
lynx/format.py
lynx.egg-info/PKG-INFO
lynx.egg-info/SOURCES.txt
lynx.egg-info/dependency_links.txt
lynx.egg-info/top_level.txt
tests/__init__.py
tests/test_decode.py
tests/test_encode.py
tests/config_files/fields.conf
tests/config_files/lists.conf
tests/config_files/multiline.conf
tests/config_files/nums.conf
tests/config_files/sections.conf
tests/config_files/wrong_format.conf
tests/config_files/wrong_list.conf