Metadata-Version: 1.0
Name: lynx
Version: 0.3.1
Summary: Python configuration library
Home-page: https://github.com/omershelef/lynx/
Author: Omer Shelef
Author-email: shlaflaf@gmail.com
License: The MIT License (MIT)
Platform: UNKNOWN
